[
  {
    "text": "君不见高堂明镜悲白发",
    "emotion": "✨ 灵感",
    "timestamp": "2026-01-27 14:27"
  },
  {
    "text": "山色空蒙，云绕峰峦，溪声入耳，心随风远，步履轻盈。",
    "emotion": "✨ 灵感",
    "timestamp": "2026-01-27 15:09"
  },
  {
    "text": "山色空蒙，云绕峰峦，溪声入耳，心随风远，步履轻盈。",
    "emotion": "✨ 灵感",
    "timestamp": "2026-01-27 15:09"
  },
  {
    "text": "溪声真的能入耳吗？",
    "emotion": "✨ 灵感",
    "timestamp": "2026-01-27 15:10"
  },
  {
    "text": "哈哈哈哈",
    "emotion": "✨ 灵感",
    "timestamp": "2026-01-27 15:24"
  },
  {
    "text": "哈哈哈哈",
    "emotion": "✨ 灵感",
    "timestamp": "2026-01-27 15:24"
  },
  {
    "text": "哈哈哈哈",
    "emotion": "✨ 灵感",
    "timestamp": "2026-01-27 15:24"
  },
  {
    "text": "我喜欢大海的蓝色",
    "emotion": "✨ 灵感",
    "timestamp": "2026-01-27 15:30"
  },
  {
    "text": "你喜欢高山吗",
    "emotion": "✨ 灵感",
    "timestamp": "2026-01-27 15:30"
  },
  {
    "text": "美丽的田园生活，好多羊",
    "emotion": "✨ 灵感",
    "timestamp": "2026-01-27 15:30"
  },
  {
    "text": "是那“山色空蒙”，仿佛山雾把世界都揉成画。",
    "emotion": "✨ 灵感",
    "timestamp": "2026-01-27 15:30"
  },
  {
    "text": "因为站在高处，风把烦恼都带走了，心也跟着自由飞。",
    "emotion": "✨ 灵感",
    "timestamp": "2026-01-27 15:31"
  },
  {
    "text": "当然，清澈溪水叮咚响，好像在弹一首旅途的歌。",
    "emotion": "✨ 灵感",
    "timestamp": "2026-01-27 15:31"
  },
  {
    "text": "当然，清澈溪水叮咚响，好像在弹一首旅途的歌。",
    "emotion": "✨ 灵感",
    "timestamp": "2026-01-27 15:31"
  },
  {
    "text": "我喜欢大海的蓝色",
    "emotion": "✨ 灵感",
    "timestamp": "2026-01-27 15:32"
  },
  {
    "text": "我喜欢大海的蓝色",
    "emotion": "✨ 灵感",
    "timestamp": "2026-01-27 15:32"
  },
  {
    "text": "我喜欢大海的蓝色",
    "emotion": "✨ 灵感",
    "timestamp": "2026-01-27 15:32"
  },
  {
    "text": "我喜欢大海的蓝色",
    "emotion": "✨ 灵感",
    "timestamp": "2026-01-27 15:33"
  },
  {
    "text": "我喜欢大海的蓝色",
    "emotion": "✨ 灵感",
    "timestamp": "2026-01-27 15:34"
  },
  {
    "text": "我喜欢大海的蓝色",
    "emotion": "✨ 灵感",
    "timestamp": "2026-01-27 15:34"
  },
  {
    "text": "我喜欢大海的蓝色",
    "emotion": "🎨 创意",
    "timestamp": "2026-01-27 15:34"
  },
  {
    "text": "我在圣托里尼",
    "emotion": "🎨 创意",
    "timestamp": "2026-01-27 15:35"
  },
  {
    "text": "我在圣托里尼",
    "emotion": "🎨 创意",
    "timestamp": "2026-01-27 15:37"
  },
  {
    "text": "我在海边写生",
    "emotion": "🎨 创意",
    "timestamp": "2026-01-27 15:38"
  },
  {
    "text": "我在海边，这里的风好大，天好蓝",
    "emotion": "✨ 灵感",
    "timestamp": "2026-01-27 15:47"
  },
  {
    "text": "我在海边，这里的风好大，天好蓝",
    "emotion": "✨ 灵感",
    "timestamp": "2026-01-27 15:47"
  },
  {
    "text": "我喜欢大海",
    "emotion": "✨ 灵感",
    "timestamp": "2026-01-27 16:13"
  },
  {
    "text": "我好喜欢大海",
    "emotion": "✨ 灵感",
    "timestamp": "2026-01-27 16:21"
  }
]